qdldl.cpython-310-aarch64-linux-gnu.so
qdldl-0.1.7.post5.dist-info/top_level.txt
qdldl-0.1.7.post5.dist-info/RECORD
qdldl-0.1.7.post5.dist-info/LICENSE
qdldl-0.1.7.post5.dist-info/METADATA
qdldl-0.1.7.post5.dist-info/WHEEL
