Metadata-Version: 2.1
Name: qdldl
Version: 0.1.7.post5
Summary: QDLDL, a free LDL factorization routine.
Home-page: https://github.com/oxfordcontrol/qdldl-python/
Author: Bartolomeo Stellato, Paul Goulart, Goran Banjac
Author-email: bartolomeo.stellato@gmail.com
License: Apache 2.0
License-File: LICENSE
Requires-Dist: numpy >=1.7
Requires-Dist: scipy >=0.13.2
